dashdaemon/__init__.py
dashdaemon/__main__.py
dashdaemon/daemon.py
dashdaemon/keys.py
dashdaemon/work.py
carpi_dashdaemon-0.2.0.dist-info/LICENSE
carpi_dashdaemon-0.2.0.dist-info/METADATA
carpi_dashdaemon-0.2.0.dist-info/WHEEL
carpi_dashdaemon-0.2.0.dist-info/top_level.txt
carpi_dashdaemon-0.2.0.dist-info/RECORD
